[
  {
    "tag": "gaming",
    "count": 378
  },
  {
    "tag": "technológia",
    "count": 374
  },
  {
    "tag": "ForHim",
    "count": 342
  },
  {
    "tag": "ign",
    "count": 281
  },
  {
    "tag": "streaming",
    "count": 208
  },
  {
    "tag": "sorozat",
    "count": 185
  },
  {
    "tag": "mozi",
    "count": 180
  },
  {
    "tag": "életmód",
    "count": 178
  },
  {
    "tag": "szórakozás",
    "count": 175
  },
  {
    "tag": "mesterséges intelligencia",
    "count": 172
  },
  {
    "tag": "gazdaság",
    "count": 167
  },
  {
    "tag": "hollywood",
    "count": 165
  },
  {
    "tag": "videojáték",
    "count": 165
  },
  {
    "tag": "infopctech",
    "count": 159
  },
  {
    "tag": "autóipar",
    "count": 152
  },
  {
    "tag": "kultúra",
    "count": 148
  },
  {
    "tag": "tudomány",
    "count": 141
  },
  {
    "tag": "budapest",
    "count": 134
  },
  {
    "tag": "kriptovaluta",
    "count": 133
  },
  {
    "tag": "pcgamer",
    "count": 132
  },
  {
    "tag": "befektetés",
    "count": 128
  },
  {
    "tag": "24",
    "count": 119
  },
  {
    "tag": "index",
    "count": 118
  },
  {
    "tag": "techpowerup",
    "count": 115
  },
  {
    "tag": "magyarország",
    "count": 115
  },
  {
    "tag": "usa",
    "count": 114
  },
  {
    "tag": "cointelegraph",
    "count": 113
  },
  {
    "tag": "gsplus",
    "count": 108
  },
  {
    "tag": "femina",
    "count": 108
  },
  {
    "tag": "elektromos autó",
    "count": 107
  },
  {
    "tag": "steam",
    "count": 102
  },
  {
    "tag": "drive",
    "count": 102
  },
  {
    "tag": "ai",
    "count": 101
  },
  {
    "tag": "közlekedés",
    "count": 101
  },
  {
    "tag": "sorozatjunkie",
    "count": 99
  },
  {
    "tag": "hardver",
    "count": 96
  },
  {
    "tag": "pcguru",
    "count": 95
  },
  {
    "tag": "videójáték",
    "count": 94
  },
  {
    "tag": "gamingbible",
    "count": 93
  },
  {
    "tag": "utazás",
    "count": 92
  },
  {
    "tag": "port",
    "count": 91
  },
  {
    "tag": "vezess",
    "count": 91
  },
  {
    "tag": "marieclaire",
    "count": 91
  },
  {
    "tag": "games",
    "count": 90
  },
  {
    "tag": "netflix",
    "count": 90
  },
  {
    "tag": "techcrunch",
    "count": 86
  },
  {
    "tag": "televízió",
    "count": 85
  },
  {
    "tag": "popkultúra",
    "count": 84
  },
  {
    "tag": "nasa",
    "count": 84
  },
  {
    "tag": "gasztronómia",
    "count": 83
  },
  {
    "tag": "rpg",
    "count": 83
  },
  {
    "tag": "totalcar",
    "count": 83
  },
  {
    "tag": "celeb",
    "count": 81
  },
  {
    "tag": "film",
    "count": 81
  },
  {
    "tag": "nlc",
    "count": 80
  },
  {
    "tag": "egészség",
    "count": 79
  },
  {
    "tag": "bulvár",
    "count": 79
  },
  {
    "tag": "esport1",
    "count": 79
  },
  {
    "tag": "turizmus",
    "count": 78
  },
  {
    "tag": "cnet",
    "count": 78
  },
  {
    "tag": "roadster",
    "count": 77
  },
  {
    "tag": "mafab",
    "count": 77
  },
  {
    "tag": "sci-fi",
    "count": 76
  },
  {
    "tag": "akció",
    "count": 75
  },
  {
    "tag": "kutatás",
    "count": 74
  },
  {
    "tag": "blokklánc",
    "count": 74
  },
  {
    "tag": "bitcoin",
    "count": 74
  },
  {
    "tag": "pénzügy",
    "count": 73
  },
  {
    "tag": "űrkutatás",
    "count": 70
  },
  {
    "tag": "divat",
    "count": 70
  },
  {
    "tag": "nintendo",
    "count": 69
  },
  {
    "tag": "húsvét",
    "count": 69
  },
  {
    "tag": "pc",
    "count": 68
  },
  {
    "tag": "pc gaming",
    "count": 67
  },
  {
    "tag": "xbox",
    "count": 67
  },
  {
    "tag": "hvg",
    "count": 67
  },
  {
    "tag": "telex",
    "count": 65
  },
  {
    "tag": "innováció",
    "count": 65
  },
  {
    "tag": "játékfejlesztés",
    "count": 64
  },
  {
    "tag": "forbes",
    "count": 63
  },
  {
    "tag": "történelem",
    "count": 62
  },
  {
    "tag": "pszichológia",
    "count": 62
  },
  {
    "tag": "tech",
    "count": 62
  },
  {
    "tag": "sport",
    "count": 62
  },
  {
    "tag": "horror",
    "count": 60
  },
  {
    "tag": "fenntarthatóság",
    "count": 60
  },
  {
    "tag": "közösségi média",
    "count": 59
  },
  {
    "tag": "sony",
    "count": 58
  },
  {
    "tag": "decrypt",
    "count": 58
  },
  {
    "tag": "kína",
    "count": 58
  },
  {
    "tag": "tőzsde",
    "count": 56
  },
  {
    "tag": "prohardver",
    "count": 55
  },
  {
    "tag": "biztonság",
    "count": 55
  },
  {
    "tag": "pcwplus",
    "count": 55
  },
  {
    "tag": "space",
    "count": 55
  },
  {
    "tag": "playstation",
    "count": 54
  },
  {
    "tag": "pc játék",
    "count": 54
  },
  {
    "tag": "zene",
    "count": 54
  },
  {
    "tag": "csillagászat",
    "count": 53
  },
  {
    "tag": "üzlet",
    "count": 53
  }
]