[
  {
    "id": "0fce2818-9f6a-4bf2-9a08-c2e498c0f048",
    "title": "BoardGameGeek Hotness",
    "content": "1. **Brass: Pittsburgh**\n*2027*\nTake part in the United States' late 19th-century industrial boom.\n![Brass: Pittsburgh](https://raw.githubusercontent.com/Derushir/Kepek/main/2026-04-08/toplist/bgg_7cee4ee9.png)\n\n2. **The Lord of the Rings: Fate of the Fellowship**\n*2025*\nAs members of The Fellowship, embark on a journey to save—or doom—Middle-earth.\n![The Lord of the Rings: Fate of the Fellowship](https://raw.githubusercontent.com/Derushir/Kepek/main/2026-04-08/toplist/bgg_4070a2bd.png)\n\n3. **Nippon: Zaibatsu**\n*2026*\nControl conglomerates of companies driving Japan’s economy.\n![Nippon: Zaibatsu](https://raw.githubusercontent.com/Derushir/Kepek/main/2026-04-08/toplist/bgg_706c63f3.jpg)\n\n4. **Arcs**\n*2024*\nRule the galaxy with your court, fleet, and cities.\n![Arcs](https://raw.githubusercontent.com/Derushir/Kepek/main/2026-04-08/toplist/bgg_4f05e25c.png)\n\n5. **Gods & Mortals**\n*2026*\nA rare blend of stock trading and area control set in Homeric Greece.\n![Gods & Mortals](https://raw.githubusercontent.com/Derushir/Kepek/main/2026-04-08/toplist/bgg_a8e84cb5.jpg)\n\n6. **The Lord of the Rings: The King's Gambit**\n*2027*\nThe climactic final battles in The Lord of The Rings come alive on an epic board.\n![The Lord of the Rings: The King's Gambit](https://raw.githubusercontent.com/Derushir/Kepek/main/2026-04-08/toplist/bgg_3d0048e6.jpg)\n\n7. **Eternal Decks**\n*2025*\nCan you solve each stage before your deck runs out?\n![Eternal Decks](https://raw.githubusercontent.com/Derushir/Kepek/main/2026-04-08/toplist/bgg_9f386083.png)\n\n8. **Brass: Birmingham**\n*2018*\nBuild networks, grow industries, and navigate the world of the Industrial Revolution.\n![Brass: Birmingham](https://raw.githubusercontent.com/Derushir/Kepek/main/2026-04-08/toplist/bgg_a3e4769f.jpg)\n\n9. **SETI: Search for Extraterrestrial Intelligence**\n*2024*\nSearch for signs of alien life by launching probes and analyzing distant signals.\n![SETI: Search for Extraterrestrial Intelligence](https://raw.githubusercontent.com/Derushir/Kepek/main/2026-04-08/toplist/bgg_d06e9288.jpg)\n\n10. **Goa**\n*2004*\nRun a spice trade business in colonial-era India in this closed-loop economy game.\n![Goa](https://raw.githubusercontent.com/Derushir/Kepek/main/2026-04-08/toplist/bgg_ce9bd8ec.jpg)\n\n11. **Arkham Horror: The Card Game**\n*2026*\nInvestigate the mysteries of Arkham while cosmic horrors stand in your way.\n![Arkham Horror: The Card Game](https://raw.githubusercontent.com/Derushir/Kepek/main/2026-04-08/toplist/bgg_c50be43c.png)\n\n12. **Slay the Spire: The Board Game**\n*2024*\nCraft a unique deck, discover powerful relics, and Slay the Spire together!\n![Slay the Spire: The Board Game](https://raw.githubusercontent.com/Derushir/Kepek/main/2026-04-08/toplist/bgg_d9b5eea4.png)\n\n13. **The Great Sea**\n*2026*\nConstruct biremes, fortify trade routes, and control the ancient temples.\n![The Great Sea](https://raw.githubusercontent.com/Derushir/Kepek/main/2026-04-08/toplist/bgg_fd532032.png)\n\n14. **Ark Nova**\n*2021*\nPlan and build a modern, scientifically managed zoo to support conservation projects.\n![Ark Nova](https://raw.githubusercontent.com/Derushir/Kepek/main/2026-04-08/toplist/bgg_14645859.jpg)\n\n15. **Heat: Pedal to the Metal**\n*2022*\nPush your car to the limit in the pursuit of victory, but don’t overheat!\n![Heat: Pedal to the Metal](https://raw.githubusercontent.com/Derushir/Kepek/main/2026-04-08/toplist/bgg_e4b55e3d.jpg)\n\n16. **The Old King's Crown**\n*2025*\nOut-manoeuvre your rivals as you vie for control of an ancient, crumbling kingdom.\n\n17. **Dune: Imperium – Uprising**\n*2023*\nDeploy agents, build your deck, and engage in strategic battles to control Arrakis.\n![Dune: Imperium – Uprising](https://raw.githubusercontent.com/Derushir/Kepek/main/2026-04-08/toplist/bgg_98b9e4a6.jpg)\n\n18. **Magical Athlete**\n*2025*\nPit a cast of crazy characters against each other in a madcap race to the finish.\n![Magical Athlete](https://raw.githubusercontent.com/Derushir/Kepek/main/2026-04-08/toplist/bgg_b9d7a9d8.png)\n\n19. **Arkham Horror: The Card Game**\n*2016*\nInvestigate the horrors of Arkham while courting cosmic doom.\n![Arkham Horror: The Card Game](https://raw.githubusercontent.com/Derushir/Kepek/main/2026-04-08/toplist/bgg_a795132e.jpg)\n\n20. **Cozy Stickerville**\n*2026*\nBuild your village with over 800 stickers! \n![Cozy Stickerville](https://raw.githubusercontent.com/Derushir/Kepek/main/2026-04-08/toplist/bgg_e4dd84bc.jpg)\n\n21. **Root**\n*2018*\nDecide the fate of the woodland as asymmetric factions fight for contrasting goals.\n![Root](https://raw.githubusercontent.com/Derushir/Kepek/main/2026-04-08/toplist/bgg_64098254.jpg)\n\n22. **Speakeasy**\n*2025*\nEarn money running a Manhattan speakeasy business during Prohibition.\n![Speakeasy](https://raw.githubusercontent.com/Derushir/Kepek/main/2026-04-08/toplist/bgg_5f003ca5.jpg)\n\n23. **Spirit Island**\n*2017*\nIsland Spirits join forces using elemental powers to defend their home from invaders.\n![Spirit Island](https://raw.githubusercontent.com/Derushir/Kepek/main/2026-04-08/toplist/bgg_1d81d82c.jpg)\n\n24. **Terraforming Mars**\n*2016*\nCompete with rival CEOs to make Mars habitable and build your corporate empire.\n![Terraforming Mars](https://raw.githubusercontent.com/Derushir/Kepek/main/2026-04-08/toplist/bgg_9c213c16.jpg)\n\n25. **Wondrous Creatures**\n*2024*\nBuild the best reserve in the world for 100+ fantastic creatures!\n![Wondrous Creatures](https://raw.githubusercontent.com/Derushir/Kepek/main/2026-04-08/toplist/bgg_ddc1bfdb.jpg)\n",
    "category": "SZÓRAKOZÁS",
    "tags": [
      "toplista",
      "rangsor",
      "kedvencek",
      "ajánló",
      "top10",
      "kultúra",
      "szórakozás",
      "trend",
      "népszerű",
      "válogatás",
      "boardgamegeek.com"
    ],
    "importance": 4,
    "image": "https://raw.githubusercontent.com/Derushir/Kepek/main/2026-04-08/toplist/bgg_7cee4ee9.png",
    "image_links": [
      "https://raw.githubusercontent.com/Derushir/Kepek/main/2026-04-08/toplist/bgg_7cee4ee9.png",
      "https://raw.githubusercontent.com/Derushir/Kepek/main/2026-04-08/toplist/bgg_4070a2bd.png",
      "https://raw.githubusercontent.com/Derushir/Kepek/main/2026-04-08/toplist/bgg_706c63f3.jpg",
      "https://raw.githubusercontent.com/Derushir/Kepek/main/2026-04-08/toplist/bgg_4f05e25c.png",
      "https://raw.githubusercontent.com/Derushir/Kepek/main/2026-04-08/toplist/bgg_a8e84cb5.jpg",
      "https://raw.githubusercontent.com/Derushir/Kepek/main/2026-04-08/toplist/bgg_3d0048e6.jpg",
      "https://raw.githubusercontent.com/Derushir/Kepek/main/2026-04-08/toplist/bgg_9f386083.png",
      "https://raw.githubusercontent.com/Derushir/Kepek/main/2026-04-08/toplist/bgg_a3e4769f.jpg",
      "https://raw.githubusercontent.com/Derushir/Kepek/main/2026-04-08/toplist/bgg_d06e9288.jpg",
      "https://raw.githubusercontent.com/Derushir/Kepek/main/2026-04-08/toplist/bgg_ce9bd8ec.jpg",
      "https://raw.githubusercontent.com/Derushir/Kepek/main/2026-04-08/toplist/bgg_c50be43c.png",
      "https://raw.githubusercontent.com/Derushir/Kepek/main/2026-04-08/toplist/bgg_d9b5eea4.png",
      "https://raw.githubusercontent.com/Derushir/Kepek/main/2026-04-08/toplist/bgg_fd532032.png",
      "https://raw.githubusercontent.com/Derushir/Kepek/main/2026-04-08/toplist/bgg_14645859.jpg",
      "https://raw.githubusercontent.com/Derushir/Kepek/main/2026-04-08/toplist/bgg_e4b55e3d.jpg",
      "",
      "https://raw.githubusercontent.com/Derushir/Kepek/main/2026-04-08/toplist/bgg_98b9e4a6.jpg",
      "https://raw.githubusercontent.com/Derushir/Kepek/main/2026-04-08/toplist/bgg_b9d7a9d8.png",
      "https://raw.githubusercontent.com/Derushir/Kepek/main/2026-04-08/toplist/bgg_a795132e.jpg",
      "https://raw.githubusercontent.com/Derushir/Kepek/main/2026-04-08/toplist/bgg_e4dd84bc.jpg",
      "https://raw.githubusercontent.com/Derushir/Kepek/main/2026-04-08/toplist/bgg_64098254.jpg",
      "https://raw.githubusercontent.com/Derushir/Kepek/main/2026-04-08/toplist/bgg_5f003ca5.jpg",
      "https://raw.githubusercontent.com/Derushir/Kepek/main/2026-04-08/toplist/bgg_1d81d82c.jpg",
      "https://raw.githubusercontent.com/Derushir/Kepek/main/2026-04-08/toplist/bgg_9c213c16.jpg",
      "https://raw.githubusercontent.com/Derushir/Kepek/main/2026-04-08/toplist/bgg_ddc1bfdb.jpg"
    ],
    "sourceLink": "https://boardgamegeek.com/hotness",
    "author": "boardgamegeek.com",
    "processed_by": "toplist_generator",
    "originalTitle": "BoardGameGeek Hotness"
  },
  {
    "id": "d7304727-0d17-4c3f-b084-aaf540195d57",
    "title": "BoardGameGeek Bestsellers (Fallback to Plays)",
    "content": "1. **Flip 7**\n*15 months on the list*\nScore the cards in front of you, or take another card, risking everything you hold?\n![Flip 7](https://raw.githubusercontent.com/Derushir/Kepek/main/2026-04-08/toplist/bgg_2cf4d4ff.jpg)\n\n2. **Harmonies**\n*23 months on the list*\nCreate your own landscape and habitats to welcome animals.\n![Harmonies](https://raw.githubusercontent.com/Derushir/Kepek/main/2026-04-08/toplist/bgg_257fa349.jpg)\n\n3. **Castle Combo**\n*18 months on the list*\nCombine medieval villagers and castle dwellers to score points.\n![Castle Combo](https://raw.githubusercontent.com/Derushir/Kepek/main/2026-04-08/toplist/bgg_bed63877.jpg)\n\n4. **Ark Nova**\n*51 months on the list*\nPlan and build a modern, scientifically managed zoo to support conservation projects.\n![Ark Nova](https://raw.githubusercontent.com/Derushir/Kepek/main/2026-04-08/toplist/bgg_6a03c554.jpg)\n\n5. **Wingspan**\n*87 months on the list*\nAttract a beautiful and diverse collection of birds to your wildlife preserve.\n![Wingspan](https://raw.githubusercontent.com/Derushir/Kepek/main/2026-04-08/toplist/bgg_02f924f3.jpg)\n\n6. **Bomb Busters**\n*11 months on the list*\nPlayers defuse bombs by deducing and cutting unseen wires of different values.\n![Bomb Busters](https://raw.githubusercontent.com/Derushir/Kepek/main/2026-04-08/toplist/bgg_7fcf72f1.png)\n\n7. **Heat: Pedal to the Metal**\n*40 months on the list*\nPush your car to the limit in the pursuit of victory, but don’t overheat!\n![Heat: Pedal to the Metal](https://raw.githubusercontent.com/Derushir/Kepek/main/2026-04-08/toplist/bgg_edc93dd9.jpg)\n\n8. **Azul**\n*101 months on the list*\nArtfully embellish the walls of your palace by drafting the most beautiful tiles.\n![Azul](https://raw.githubusercontent.com/Derushir/Kepek/main/2026-04-08/toplist/bgg_d2a84884.png)\n\n9. **Terraforming Mars**\n*114 months on the list*\nCompete with rival CEOs to make Mars habitable and build your corporate empire.\n![Terraforming Mars](https://raw.githubusercontent.com/Derushir/Kepek/main/2026-04-08/toplist/bgg_71c6eedb.jpg)\n\n10. **Sea Salt & Paper**\n*33 months on the list*\nA few delicate Origami-style illustrations and a whole marine universe comes to life!\n![Sea Salt & Paper](https://raw.githubusercontent.com/Derushir/Kepek/main/2026-04-08/toplist/bgg_0d40151f.jpg)\n\n11. **Forest Shuffle**\n*30 months on the list*\nCurate a diverse ecology with strategic flora and fauna, winter is coming!\n![Forest Shuffle](https://raw.githubusercontent.com/Derushir/Kepek/main/2026-04-08/toplist/bgg_a426f123.jpg)\n\n12. **Cascadia**\n*56 months on the list*\nCreate the most harmonious ecosystem as you puzzle together habitats and wildlife.\n![Cascadia](https://raw.githubusercontent.com/Derushir/Kepek/main/2026-04-08/toplist/bgg_259689aa.jpg)\n\n13. **Lost Ruins of Arnak**\n*63 months on the list*\nExplore an island to find resources and discover the lost ruins of Arnak.\n![Lost Ruins of Arnak](https://raw.githubusercontent.com/Derushir/Kepek/main/2026-04-08/toplist/bgg_88f4d9b9.jpg)\n\n14. **SETI: Search for Extraterrestrial Intelligence**\n*16 months on the list*\nSearch for signs of alien life by launching probes and analyzing distant signals.\n![SETI: Search for Extraterrestrial Intelligence](https://raw.githubusercontent.com/Derushir/Kepek/main/2026-04-08/toplist/bgg_48364b41.jpg)\n\n15. **Faraway**\n*23 months on the list*\nExplore a mysterious land and fulfill quests on your way back.\n![Faraway](https://raw.githubusercontent.com/Derushir/Kepek/main/2026-04-08/toplist/bgg_6629ff79.png)\n\n16. **Sky Team**\n*30 months on the list*\nWork together silently to land a plane under increasingly challenging circumstances.\n![Sky Team](https://raw.githubusercontent.com/Derushir/Kepek/main/2026-04-08/toplist/bgg_3234de79.jpg)\n\n17. **Hot Streak**\n*2 months on the list*\nWhich mascot will cross the finish line first? Who will be DQ'd?\n![Hot Streak](https://raw.githubusercontent.com/Derushir/Kepek/main/2026-04-08/toplist/bgg_3f7f4a98.jpg)\n\n18. **Magical Athlete**\n*2 months on the list*\nPit a cast of crazy characters against each other in a madcap race to the finish.\n![Magical Athlete](https://raw.githubusercontent.com/Derushir/Kepek/main/2026-04-08/toplist/bgg_018998e2.png)\n\n19. **The Gang**\n*9 months on the list*\nBet together the order of your hands in Texas Hold'em Poker to win together.\n![The Gang](https://raw.githubusercontent.com/Derushir/Kepek/main/2026-04-08/toplist/bgg_a97cfa4a.jpg)\n\n20. **The Lord of the Rings: The Fellowship of the Ring – Trick-Taking Game**\n*9 months on the list*\nTravel from the Shire and overcome every obstacle as a team.\n![The Lord of the Rings: The Fellowship of the Ring – Trick-Taking Game](https://raw.githubusercontent.com/Derushir/Kepek/main/2026-04-08/toplist/bgg_603f54d5.jpg)\n\n21. **The White Castle**\n*29 months on the list*\nBecome the most influential clan in Japan's Himeji stronghold.\n![The White Castle](https://raw.githubusercontent.com/Derushir/Kepek/main/2026-04-08/toplist/bgg_3ee2fd46.jpg)\n\n22. **Carcassonne**\n*273 months on the list*\nShape the medieval French landscape, claiming cities, monasteries, roads, and farms.\n![Carcassonne](https://raw.githubusercontent.com/Derushir/Kepek/main/2026-04-08/toplist/bgg_b51b8575.jpg)\n\n23. **Toy Battle**\n*2 months on the list*\nSend forth an army of toys to conquer territories.\n![Toy Battle](https://raw.githubusercontent.com/Derushir/Kepek/main/2026-04-08/toplist/bgg_ef8a9250.jpg)\n\n24. **Brass: Birmingham**\n*16 months on the list*\nBuild networks, grow industries, and navigate the world of the Industrial Revolution.\n![Brass: Birmingham](https://raw.githubusercontent.com/Derushir/Kepek/main/2026-04-08/toplist/bgg_1d1329b6.jpg)\n\n25. **Splendor**\n*143 months on the list*\nRenaissance merchants race to grab gems, acquire property, and please nobility.\n![Splendor](https://raw.githubusercontent.com/Derushir/Kepek/main/2026-04-08/toplist/bgg_26f93afb.jpg)\n",
    "category": "SZÓRAKOZÁS",
    "tags": [
      "toplista",
      "rangsor",
      "kedvencek",
      "ajánló",
      "top10",
      "kultúra",
      "szórakozás",
      "trend",
      "népszerű",
      "válogatás",
      "boardgamegeek.com"
    ],
    "importance": 4,
    "image": "https://raw.githubusercontent.com/Derushir/Kepek/main/2026-04-08/toplist/bgg_2cf4d4ff.jpg",
    "image_links": [
      "https://raw.githubusercontent.com/Derushir/Kepek/main/2026-04-08/toplist/bgg_2cf4d4ff.jpg",
      "https://raw.githubusercontent.com/Derushir/Kepek/main/2026-04-08/toplist/bgg_257fa349.jpg",
      "https://raw.githubusercontent.com/Derushir/Kepek/main/2026-04-08/toplist/bgg_bed63877.jpg",
      "https://raw.githubusercontent.com/Derushir/Kepek/main/2026-04-08/toplist/bgg_6a03c554.jpg",
      "https://raw.githubusercontent.com/Derushir/Kepek/main/2026-04-08/toplist/bgg_02f924f3.jpg",
      "https://raw.githubusercontent.com/Derushir/Kepek/main/2026-04-08/toplist/bgg_7fcf72f1.png",
      "https://raw.githubusercontent.com/Derushir/Kepek/main/2026-04-08/toplist/bgg_edc93dd9.jpg",
      "https://raw.githubusercontent.com/Derushir/Kepek/main/2026-04-08/toplist/bgg_d2a84884.png",
      "https://raw.githubusercontent.com/Derushir/Kepek/main/2026-04-08/toplist/bgg_71c6eedb.jpg",
      "https://raw.githubusercontent.com/Derushir/Kepek/main/2026-04-08/toplist/bgg_0d40151f.jpg",
      "https://raw.githubusercontent.com/Derushir/Kepek/main/2026-04-08/toplist/bgg_a426f123.jpg",
      "https://raw.githubusercontent.com/Derushir/Kepek/main/2026-04-08/toplist/bgg_259689aa.jpg",
      "https://raw.githubusercontent.com/Derushir/Kepek/main/2026-04-08/toplist/bgg_88f4d9b9.jpg",
      "https://raw.githubusercontent.com/Derushir/Kepek/main/2026-04-08/toplist/bgg_48364b41.jpg",
      "https://raw.githubusercontent.com/Derushir/Kepek/main/2026-04-08/toplist/bgg_6629ff79.png",
      "https://raw.githubusercontent.com/Derushir/Kepek/main/2026-04-08/toplist/bgg_3234de79.jpg",
      "https://raw.githubusercontent.com/Derushir/Kepek/main/2026-04-08/toplist/bgg_3f7f4a98.jpg",
      "https://raw.githubusercontent.com/Derushir/Kepek/main/2026-04-08/toplist/bgg_018998e2.png",
      "https://raw.githubusercontent.com/Derushir/Kepek/main/2026-04-08/toplist/bgg_a97cfa4a.jpg",
      "https://raw.githubusercontent.com/Derushir/Kepek/main/2026-04-08/toplist/bgg_603f54d5.jpg",
      "https://raw.githubusercontent.com/Derushir/Kepek/main/2026-04-08/toplist/bgg_3ee2fd46.jpg",
      "https://raw.githubusercontent.com/Derushir/Kepek/main/2026-04-08/toplist/bgg_b51b8575.jpg",
      "https://raw.githubusercontent.com/Derushir/Kepek/main/2026-04-08/toplist/bgg_ef8a9250.jpg",
      "https://raw.githubusercontent.com/Derushir/Kepek/main/2026-04-08/toplist/bgg_1d1329b6.jpg",
      "https://raw.githubusercontent.com/Derushir/Kepek/main/2026-04-08/toplist/bgg_26f93afb.jpg"
    ],
    "sourceLink": "https://boardgamegeek.com/trends/bestsellers",
    "author": "boardgamegeek.com",
    "processed_by": "toplist_generator",
    "originalTitle": "BoardGameGeek Bestsellers (Fallback to Plays)"
  },
  {
    "id": "507f5c92-9e3e-4282-a5b2-e79fa5890af5",
    "title": "BoardGameGeek Most Played",
    "content": "1. **Flip 7**\n*15 months on the list*\nScore the cards in front of you, or take another card, risking everything you hold?\n![Flip 7](https://raw.githubusercontent.com/Derushir/Kepek/main/2026-04-08/toplist/bgg_4793dea2.jpg)\n\n2. **Harmonies**\n*23 months on the list*\nCreate your own landscape and habitats to welcome animals.\n![Harmonies](https://raw.githubusercontent.com/Derushir/Kepek/main/2026-04-08/toplist/bgg_2291f0b7.jpg)\n\n3. **Castle Combo**\n*18 months on the list*\nCombine medieval villagers and castle dwellers to score points.\n![Castle Combo](https://raw.githubusercontent.com/Derushir/Kepek/main/2026-04-08/toplist/bgg_b36051e6.jpg)\n\n4. **Ark Nova**\n*51 months on the list*\nPlan and build a modern, scientifically managed zoo to support conservation projects.\n![Ark Nova](https://raw.githubusercontent.com/Derushir/Kepek/main/2026-04-08/toplist/bgg_fc59b54d.jpg)\n\n5. **Wingspan**\n*87 months on the list*\nAttract a beautiful and diverse collection of birds to your wildlife preserve.\n![Wingspan](https://raw.githubusercontent.com/Derushir/Kepek/main/2026-04-08/toplist/bgg_7d2c585e.jpg)\n\n6. **Bomb Busters**\n*11 months on the list*\nPlayers defuse bombs by deducing and cutting unseen wires of different values.\n![Bomb Busters](https://raw.githubusercontent.com/Derushir/Kepek/main/2026-04-08/toplist/bgg_0aa7722c.png)\n\n7. **Heat: Pedal to the Metal**\n*40 months on the list*\nPush your car to the limit in the pursuit of victory, but don’t overheat!\n![Heat: Pedal to the Metal](https://raw.githubusercontent.com/Derushir/Kepek/main/2026-04-08/toplist/bgg_44309474.jpg)\n\n8. **Azul**\n*101 months on the list*\nArtfully embellish the walls of your palace by drafting the most beautiful tiles.\n![Azul](https://raw.githubusercontent.com/Derushir/Kepek/main/2026-04-08/toplist/bgg_5cb7236a.png)\n\n9. **Terraforming Mars**\n*114 months on the list*\nCompete with rival CEOs to make Mars habitable and build your corporate empire.\n![Terraforming Mars](https://raw.githubusercontent.com/Derushir/Kepek/main/2026-04-08/toplist/bgg_0b7a0a56.jpg)\n\n10. **Sea Salt & Paper**\n*33 months on the list*\nA few delicate Origami-style illustrations and a whole marine universe comes to life!\n![Sea Salt & Paper](https://raw.githubusercontent.com/Derushir/Kepek/main/2026-04-08/toplist/bgg_028840ed.jpg)\n\n11. **Forest Shuffle**\n*30 months on the list*\nCurate a diverse ecology with strategic flora and fauna, winter is coming!\n![Forest Shuffle](https://raw.githubusercontent.com/Derushir/Kepek/main/2026-04-08/toplist/bgg_d98d1666.jpg)\n\n12. **Cascadia**\n*56 months on the list*\nCreate the most harmonious ecosystem as you puzzle together habitats and wildlife.\n![Cascadia](https://raw.githubusercontent.com/Derushir/Kepek/main/2026-04-08/toplist/bgg_45a76ee7.jpg)\n\n13. **Lost Ruins of Arnak**\n*63 months on the list*\nExplore an island to find resources and discover the lost ruins of Arnak.\n![Lost Ruins of Arnak](https://raw.githubusercontent.com/Derushir/Kepek/main/2026-04-08/toplist/bgg_034cba5c.jpg)\n\n14. **SETI: Search for Extraterrestrial Intelligence**\n*16 months on the list*\nSearch for signs of alien life by launching probes and analyzing distant signals.\n![SETI: Search for Extraterrestrial Intelligence](https://raw.githubusercontent.com/Derushir/Kepek/main/2026-04-08/toplist/bgg_46c0a5e6.jpg)\n\n15. **Faraway**\n*23 months on the list*\nExplore a mysterious land and fulfill quests on your way back.\n![Faraway](https://raw.githubusercontent.com/Derushir/Kepek/main/2026-04-08/toplist/bgg_142a5dc1.png)\n\n16. **Sky Team**\n*30 months on the list*\nWork together silently to land a plane under increasingly challenging circumstances.\n![Sky Team](https://raw.githubusercontent.com/Derushir/Kepek/main/2026-04-08/toplist/bgg_46003ff7.jpg)\n\n17. **Hot Streak**\n*2 months on the list*\nWhich mascot will cross the finish line first? Who will be DQ'd?\n![Hot Streak](https://raw.githubusercontent.com/Derushir/Kepek/main/2026-04-08/toplist/bgg_e870a137.jpg)\n\n18. **Magical Athlete**\n*2 months on the list*\nPit a cast of crazy characters against each other in a madcap race to the finish.\n![Magical Athlete](https://raw.githubusercontent.com/Derushir/Kepek/main/2026-04-08/toplist/bgg_883111d7.png)\n\n19. **The Gang**\n*9 months on the list*\nBet together the order of your hands in Texas Hold'em Poker to win together.\n![The Gang](https://raw.githubusercontent.com/Derushir/Kepek/main/2026-04-08/toplist/bgg_c9a2f06c.jpg)\n\n20. **The Lord of the Rings: The Fellowship of the Ring – Trick-Taking Game**\n*9 months on the list*\nTravel from the Shire and overcome every obstacle as a team.\n![The Lord of the Rings: The Fellowship of the Ring – Trick-Taking Game](https://raw.githubusercontent.com/Derushir/Kepek/main/2026-04-08/toplist/bgg_54776ec1.jpg)\n\n21. **The White Castle**\n*29 months on the list*\nBecome the most influential clan in Japan's Himeji stronghold.\n![The White Castle](https://raw.githubusercontent.com/Derushir/Kepek/main/2026-04-08/toplist/bgg_fe71035b.jpg)\n\n22. **Carcassonne**\n*273 months on the list*\nShape the medieval French landscape, claiming cities, monasteries, roads, and farms.\n![Carcassonne](https://raw.githubusercontent.com/Derushir/Kepek/main/2026-04-08/toplist/bgg_0f0591c5.jpg)\n\n23. **Toy Battle**\n*2 months on the list*\nSend forth an army of toys to conquer territories.\n![Toy Battle](https://raw.githubusercontent.com/Derushir/Kepek/main/2026-04-08/toplist/bgg_95ee0a7f.jpg)\n\n24. **Brass: Birmingham**\n*16 months on the list*\nBuild networks, grow industries, and navigate the world of the Industrial Revolution.\n![Brass: Birmingham](https://raw.githubusercontent.com/Derushir/Kepek/main/2026-04-08/toplist/bgg_e31c94fe.jpg)\n\n25. **Splendor**\n*143 months on the list*\nRenaissance merchants race to grab gems, acquire property, and please nobility.\n![Splendor](https://raw.githubusercontent.com/Derushir/Kepek/main/2026-04-08/toplist/bgg_8d78cdec.jpg)\n",
    "category": "SZÓRAKOZÁS",
    "tags": [
      "toplista",
      "rangsor",
      "kedvencek",
      "ajánló",
      "top10",
      "kultúra",
      "szórakozás",
      "trend",
      "népszerű",
      "válogatás",
      "boardgamegeek.com"
    ],
    "importance": 4,
    "image": "https://raw.githubusercontent.com/Derushir/Kepek/main/2026-04-08/toplist/bgg_4793dea2.jpg",
    "image_links": [
      "https://raw.githubusercontent.com/Derushir/Kepek/main/2026-04-08/toplist/bgg_4793dea2.jpg",
      "https://raw.githubusercontent.com/Derushir/Kepek/main/2026-04-08/toplist/bgg_2291f0b7.jpg",
      "https://raw.githubusercontent.com/Derushir/Kepek/main/2026-04-08/toplist/bgg_b36051e6.jpg",
      "https://raw.githubusercontent.com/Derushir/Kepek/main/2026-04-08/toplist/bgg_fc59b54d.jpg",
      "https://raw.githubusercontent.com/Derushir/Kepek/main/2026-04-08/toplist/bgg_7d2c585e.jpg",
      "https://raw.githubusercontent.com/Derushir/Kepek/main/2026-04-08/toplist/bgg_0aa7722c.png",
      "https://raw.githubusercontent.com/Derushir/Kepek/main/2026-04-08/toplist/bgg_44309474.jpg",
      "https://raw.githubusercontent.com/Derushir/Kepek/main/2026-04-08/toplist/bgg_5cb7236a.png",
      "https://raw.githubusercontent.com/Derushir/Kepek/main/2026-04-08/toplist/bgg_0b7a0a56.jpg",
      "https://raw.githubusercontent.com/Derushir/Kepek/main/2026-04-08/toplist/bgg_028840ed.jpg",
      "https://raw.githubusercontent.com/Derushir/Kepek/main/2026-04-08/toplist/bgg_d98d1666.jpg",
      "https://raw.githubusercontent.com/Derushir/Kepek/main/2026-04-08/toplist/bgg_45a76ee7.jpg",
      "https://raw.githubusercontent.com/Derushir/Kepek/main/2026-04-08/toplist/bgg_034cba5c.jpg",
      "https://raw.githubusercontent.com/Derushir/Kepek/main/2026-04-08/toplist/bgg_46c0a5e6.jpg",
      "https://raw.githubusercontent.com/Derushir/Kepek/main/2026-04-08/toplist/bgg_142a5dc1.png",
      "https://raw.githubusercontent.com/Derushir/Kepek/main/2026-04-08/toplist/bgg_46003ff7.jpg",
      "https://raw.githubusercontent.com/Derushir/Kepek/main/2026-04-08/toplist/bgg_e870a137.jpg",
      "https://raw.githubusercontent.com/Derushir/Kepek/main/2026-04-08/toplist/bgg_883111d7.png",
      "https://raw.githubusercontent.com/Derushir/Kepek/main/2026-04-08/toplist/bgg_c9a2f06c.jpg",
      "https://raw.githubusercontent.com/Derushir/Kepek/main/2026-04-08/toplist/bgg_54776ec1.jpg",
      "https://raw.githubusercontent.com/Derushir/Kepek/main/2026-04-08/toplist/bgg_fe71035b.jpg",
      "https://raw.githubusercontent.com/Derushir/Kepek/main/2026-04-08/toplist/bgg_0f0591c5.jpg",
      "https://raw.githubusercontent.com/Derushir/Kepek/main/2026-04-08/toplist/bgg_95ee0a7f.jpg",
      "https://raw.githubusercontent.com/Derushir/Kepek/main/2026-04-08/toplist/bgg_e31c94fe.jpg",
      "https://raw.githubusercontent.com/Derushir/Kepek/main/2026-04-08/toplist/bgg_8d78cdec.jpg"
    ],
    "sourceLink": "https://boardgamegeek.com/trends/mostplayed",
    "author": "boardgamegeek.com",
    "processed_by": "toplist_generator",
    "originalTitle": "BoardGameGeek Most Played"
  }
]